youtube_va_downloader/__init__.py
youtube_va_downloader/__main__.py
youtube_va_downloader/download_video.py
youtube_va_downloader/format_display.py
youtube_va_downloader/icon.ico
youtube_va_downloader/search_video.py
youtube_va_downloader/set_up.py
youtube_va_downloader/setup.txt
youtube_va_downloader/youtube_downloader.py
Youtube_Video_Audio_Downloader-0.2.15.dist-info/LICENSE
Youtube_Video_Audio_Downloader-0.2.15.dist-info/METADATA
Youtube_Video_Audio_Downloader-0.2.15.dist-info/WHEEL
Youtube_Video_Audio_Downloader-0.2.15.dist-info/top_level.txt
Youtube_Video_Audio_Downloader-0.2.15.dist-info/RECORD
