Metadata-Version: 2.1
Name: Youtube-Video-Audio-Downloader
Version: 0.2.15
Summary: A Simple GUI interface to help download videos and audio files from Youtube using Youtube-dl and FFMPEG
Home-page: https://github.com/Alex-Au1/Youtube_Downloader
Author: Alex Au
Author-email: AlexXianZhenYuAu@gmail.com
Classifier: Programming Language :: Python :: 3
Classifier: License :: OSI Approved :: MIT License
Classifier: Operating System :: OS Independent
Requires-Python: >=3.6
License-File: LICENSE
Requires-Dist: Pillow
Requires-Dist: pyperclip
Requires-Dist: yt-dlp
Requires-Dist: youtube-search-python
Requires-Dist: mutagen
Requires-Dist: requests
Requires-Dist: validators
